{
  "destination_slug": "goa",
  "package": {
    "slug": "ga-015-relaxed-old-goa-temples",
    "serial_code": "GA-015",
    "traguin_tour_code": "TRG-GOA-015",
    "title": "TRAGUIN Premium Goa Tour Package — Relaxed Old Goa & Temples",
    "duration_label": "04 Nights / 05 Days",
    "price": 0,
    "sold_last_month": 0,
    "rating": "4.9",
    "is_featured": false,
    "featured_sort_order": null,
    "is_published": false,
    "highlights": [
      {
        "text": "Serial code GA-015 | TRAGUIN tour code TRG-GOA-015",
        "sort_order": 1
      },
      {
        "text": "State / Country: Goa / India | Category: Premium Senior",
        "sort_order": 2
      },
      {
        "text": "Destinations: Panaji • Old Goa • Ponda Temples • Miramar •",
        "sort_order": 3
      },
      {
        "text": "Ideal for: Senior Citizens, Family Groups & Heritage Connoisseurs",
        "sort_order": 4
      },
      {
        "text": "Best season: October to April",
        "sort_order": 5
      },
      {
        "text": "Starting price: On Request (Bespoke Senior Luxury Customised)",
        "sort_order": 6
      },
      {
        "text": "Vehicle / Meals: Private Luxury AC",
        "sort_order": 7
      },
      {
        "text": "TRAGUIN Signature Experience: VIP pre-arranged darshan entries at Ponda temples to minimize waiting",
        "sort_order": 8
      },
      {
        "text": "Curated by TRAGUIN Experts: Pacing designed with generous afternoon rest blocks, ideal for senior",
        "sort_order": 9
      },
      {
        "text": "Premium Handpicked Hotels: Properties meticulously chosen for their step-free layouts, manicured",
        "sort_order": 10
      },
      {
        "text": "Luxury Transportation: Chauffeurs skilled in defensive, smooth highway and city driving for maximum",
        "sort_order": 11
      },
      {
        "text": "Local Souvenirs: Shop for world-renowned premium Goa whole cashews, authentic local feni, handcrafted Portuguese-style azulejos ceramic tiles, and lovely clay artifacts at the Government handicraft emporium. Mouthwatering Delicacies: Sample mild Bebinca and Dodol (traditional Goan sweets), fresh coconut-based vegetarian curries, and locally made artisan fruit preserves at the spice orchard.",
        "sort_order": 12
      },
      {
        "text": "Hotel Policies: Check-in is at 14:00 hrs; check-out is at 11:00 hrs. Early check-in can be requested in",
        "sort_order": 13
      }
    ],
    "moods": [
      "Family",
      "Luxury",
      "Beach"
    ]
  },
  "itinerary": {
    "slug": "ga-015-relaxed-old-goa-temples-itinerary",
    "title": "TRAGUIN Premium Goa Tour Package — Relaxed Old Goa & Temples",
    "duration_label": "04 Nights / 05 Days",
    "duration_days": 5,
    "starting_price": 0,
    "price_note": "On Request (Bespoke Senior Luxury Customised)",
    "rating": "4.9",
    "review_count": 0,
    "tagline": "Relaxed Old Goa & Temples",
    "overview": "SERENITY Welcome to a beautifully paced, soul-stirring coastal escape curated exclusively by TRAGUIN. Designed thoughtfully as a relaxed Goa Senior Citizen Holiday, this unique itinerary invites you to discover the spiritual majesty, architectural brilliance, and peaceful rhythms of legendary Old Goa. As your dedicated luxury travel consultants, TRAGUIN ensures a perfectly balanced journey featuring premium stays, smooth low-stride transport, and immersive experiences that cater explicitly to your comfort. Witness breathtaking landscapes, historic shrines, and gentle river tides while creating unforgettable memories with absolute peace of mind.\n\nTOUR OVERVIEW\nThis custom-tailored luxury holiday package focuses deeply on comfort, accessibility, and leisurely enrichment. Travelling in a dedicated private premium AC vehicle managed by a courteous, background- verified chauffeur, our esteemed guests will encounter no hurried schedules. Our route traces a gentle, low- walking path through the beautiful Latin Quarters, grand colonial basilicas, and highly sacred spiritual sanctuaries of Ponda. With a carefully selected premium meal plan serving mild, highly refined culinary options, every detail carries the distinct TRAGUIN curated experience note, guaranteeing priority seating, wheel-chair accessibility options where needed, and continuous care.\n\nWHY CHOOSE THE BEST GOA TOUR PACKAGE FOR SENIORS?\nWhen seeking a Luxury Goa Holiday, travelers often look past the bustling nightlife to discover a realm of quiet grandeur, ancient spirituality, and timeless charm. Goa reveals its most profound cultural treasures within its majestic heritage zone, making a specialized Goa Family Tour or senior escape highly sought after. From exploring world-heritage iconic attractions like the Basilica of Bom Jesus to paying homage at the tranquil Mangueshi Temple, Goa sightseeing offers deep spiritual fulfilment. For families and seniors booking a custom Goa Honeymoon Package or an elegant heritage retreat, the destination boasts highly popular Instagram locations like the pastel-hued streets of Fontainhas and the serene spice plantations of Ponda. Indulge in authentic local handicraft shopping, relax by the calm waters of Miramar Beach, or partake in a gentle sunset cruise along the Mandovi River. Our signature TRAGUIN Goa Packages blend these exclusive experiences seamlessly with handpicked hotels, providing you the absolute best time to visit Goa with complete luxury and comfort.",
    "is_featured": false,
    "featured_sort_order": null,
    "seo_title": "GA-015 | Goa | TRAGUIN",
    "seo_description": "Premium 04 Nights / 05 Days Goa package (GA-015 / TRG-GOA-015): Panaji • Old Goa • Ponda Temples • Miramar •.",
    "is_published": false,
    "highlights": [
      {
        "text": "Day 01: ARRIVAL IN PANAJI (GOA)",
        "sort_order": 1
      },
      {
        "text": "Day 02: RELEXED OLD GOA EXPLORATION",
        "sort_order": 2
      },
      {
        "text": "Day 03: PONDA SPIRITUAL TEMPLE TOUR & SPICE ORCHARD",
        "sort_order": 3
      },
      {
        "text": "Day 04: RELEXED PANAJI SIGHTSEEING & SUNSET RIVERSIDE CRUISE",
        "sort_order": 4
      },
      {
        "text": "Day 05: DEPARTURE FROM GOA",
        "sort_order": 5
      }
    ],
    "days": [
      {
        "day_number": 1,
        "title": "ARRIVAL IN PANAJI (GOA)",
        "description": "WARM WELCOME & LATIN QUARTER AMBIANCE Your premium Goa experience begins as you step out of Mopa or Dabolim Airport, where your private luxury vehicle and an attentive chaperone await. Enjoy a smooth, scenic drive to your handpicked premium resort nestled away from the crowds. Receive a warm welcome note and refreshing amenities upon check-in. In the late afternoon, enjoy a very gentle, slow-paced drive through Fontainhas, the celebrated Latin Quarter of Panaji, filled with vibrant Portuguese-era heritage architecture and excellent photography points.",
        "activities": [
          "Sightseeing Included: Fontainhas Latin Quarter heritage drive, Altinho hill view layout.",
          "Evening Experience: Relaxed welcome high-tea and orientation session arranged by our destination manager.",
          "Overnight Stay: Panaji / Central Goa (Premium Luxury Heritage Resort)",
          "Meals Included: Welcome Drink, High Tea & Luxury Buffet Dinner"
        ],
        "sort_order": 1
      },
      {
        "day_number": 2,
        "title": "RELEXED OLD GOA EXPLORATION",
        "description": "GRAND COLONIAL ARCHITECTURE & HISTORIC BASILICAS Indulge in a wholesome breakfast before heading out to Old Goa, the former historical capital of Portuguese India. Explore the monumental Basilica of Bom Jesus, which holds the sacred remains of St. Francis Xavier, and the grand Se Cathedral across the plaza. Both sites feature flat, paved entry paths for ease of access. Enjoy immersive experiences as our expert guide narrates the deep histories behind these massive structures without any rushed timelines.",
        "activities": [
          "Sightseeing Included: Basilica of Bom Jesus, Se Cathedral, Church of St. Cajetan.",
          "Optional Activities: A quiet sitting session inside the historic, beautifully cooled prayer halls.",
          "Overnight Stay: Panaji / Central Goa (Premium Luxury Heritage Resort)",
          "Meals Included: Premium Breakfast & Gourmet Dinner"
        ],
        "sort_order": 2
      },
      {
        "day_number": 3,
        "title": "PONDA SPIRITUAL TEMPLE TOUR & SPICE ORCHARD",
        "description": "SACRED HERITAGE, SHANTI & TRADITIONAL FLAVORS Dedicate today to the sacred, peaceful temples of Ponda. Visit the highly revered 450-year-old Shri Mangueshi Temple, dedicated to Lord Shiva, known for its elegant multi-story lamp tower (Deepastambha). Next, visit the beautiful Shri Shanta Durga Temple, nestled inside a tranquil valley. Following your temple darshan, enjoy a private curated experience at a premium spice plantation, where you will receive a traditional marigold garland welcome, a slow guided level walk under lush canopies, and a mild, authentic Goan Saraswat lunch.",
        "activities": [
          "Sightseeing Included: Mangueshi Temple, Shanta Durga Temple, Sahakari Spice Farm Plantation.",
          "Evening Experience: Relaxed stroll through the spice gardens with an aromatic herbal tea tasting.",
          "Overnight Stay: Panaji / Central Goa (Premium Luxury Heritage Resort)",
          "Meals Included: Breakfast, Traditional Buffet Lunch & Dinner"
        ],
        "sort_order": 3
      },
      {
        "day_number": 4,
        "title": "RELEXED PANAJI SIGHTSEEING & SUNSET RIVERSIDE CRUISE",
        "description": "SCENIC PROMENADES & EXCLUSIVE WATERWAYS Savor a lazy morning at your resort, taking advantage of the premium luxury amenities. In the afternoon, take a comfortable drive down the scenic Miramar Beach promenade to enjoy the refreshing coastal views. Later, head towards the Mandovi River jetty to board a private luxury catamaran or premium sunset cruise liner. Watch the golden sun dip below the Arabian Sea while listening to soft local music—an exquisite way to collect unforgettable memories.",
        "activities": [
          "Sightseeing Included: Miramar Beach view drive, Panaji Church square, Mandovi River waterfront.",
          "Evening Experience: Premium Sunset Cruise on the Mandovi River with reserved lower-deck lounge seating.",
          "Overnight Stay: Panaji / Central Goa (Premium Luxury Heritage Resort)",
          "Meals Included: Breakfast & Farewell Premium Dinner"
        ],
        "sort_order": 4
      },
      {
        "day_number": 5,
        "title": "DEPARTURE FROM GOA",
        "description": "CHERISHING THE TRANQUIL MOMENTS Enjoy a leisurely final breakfast at the resort's open-air veranda. Your private luxury transportation vehicle will be ready at your preferred time to ensure a stress-free transfer back to Goa Airport or Railway Station. Return home feeling fully refreshed, carrying beautiful memories meticulously designed for you by TRAGUIN.",
        "activities": [
          "Transfers Included: Private luxury door-to-door departure drop-off.",
          "Meals Included: Sumptuous Buffet Breakfast"
        ],
        "sort_order": 5
      }
    ],
    "hotels": [
      {
        "hotel_id": null,
        "name": "Fortune Miramar / Vivanta Panaji / similar",
        "location": "Heritage & Central Goa (4 Nights)",
        "nights_label": "04 Nights",
        "description": "OPTION 01 – DELUXE: Fortune Miramar / Vivanta Panaji / similar (Heritage & Central Goa (4 Nights)) | MAPAI (Breakfast & Dinner)",
        "stars": 4,
        "category_label": "Deluxe",
        "room_type": "Superior Pool View Room",
        "meal_plan": "MAPAI (Breakfast & Dinner)",
        "image_media_id": null,
        "sort_order": 1
      },
      {
        "hotel_id": null,
        "name": "Cidade de Goa - IHCL SeleQtions / similar",
        "location": "Heritage & Central Goa (4 Nights)",
        "nights_label": "04 Nights",
        "description": "OPTION 02 – PREMIUM: Cidade de Goa - IHCL SeleQtions / similar (Heritage & Central Goa (4 Nights)) | MAPAI (Breakfast & Dinner)",
        "stars": 4,
        "category_label": "Premium",
        "room_type": "Premium Sea View Room",
        "meal_plan": "MAPAI (Breakfast & Dinner)",
        "image_media_id": null,
        "sort_order": 2
      },
      {
        "hotel_id": null,
        "name": "Taj Resort & Convention Centre Goa / similar",
        "location": "Heritage & Central Goa (4 Nights)",
        "nights_label": "04 Nights",
        "description": "OPTION 03 – LUXURY: Taj Resort & Convention Centre Goa / similar (Heritage & Central Goa (4 Nights)) | MAPAI (Breakfast & Dinner)",
        "stars": 5,
        "category_label": "Luxury",
        "room_type": "Luxury Heritage Balcony Suite",
        "meal_plan": "MAPAI (Breakfast & Dinner)",
        "image_media_id": null,
        "sort_order": 3
      },
      {
        "hotel_id": null,
        "name": "The Leela Goa / Taj Exotica Resort & Spa",
        "location": "Heritage & Central Goa (4 Nights)",
        "nights_label": "04 Nights",
        "description": "OPTION 04 – ULTRA LUXURY: The Leela Goa / Taj Exotica Resort & Spa (Heritage & Central Goa (4 Nights)) | Bespoke Personalized Dining Plan",
        "stars": 5,
        "category_label": "Ultra Luxury",
        "room_type": "VVIP Private Royal Lagoon Villa",
        "meal_plan": "Bespoke Personalized Dining Plan",
        "image_media_id": null,
        "sort_order": 4
      }
    ],
    "inclusions": [
      {
        "kind": "excluded",
        "text": "Airfare, flight tickets, or main rail transportation",
        "sort_order": 1
      },
      {
        "kind": "excluded",
        "text": "to Goa.",
        "sort_order": 2
      },
      {
        "kind": "excluded",
        "text": "Personal expenses such as laundry, phone calls,",
        "sort_order": 3
      },
      {
        "kind": "excluded",
        "text": "or tips.",
        "sort_order": 4
      },
      {
        "kind": "excluded",
        "text": "Specialized temple ritual pooja ticketing fees.",
        "sort_order": 5
      },
      {
        "kind": "excluded",
        "text": "Any water sports, beach activities, or nightlife",
        "sort_order": 6
      },
      {
        "kind": "excluded",
        "text": "excursions.",
        "sort_order": 7
      }
    ]
  }
}
